metaMS/__init__.py
metaMS/cli.py
metaMS/gcmsWorkflow.py
metaMS/metadata_factory.py
metaMS-2.1.3.dist-info/LICENSE
metaMS-2.1.3.dist-info/METADATA
metaMS-2.1.3.dist-info/WHEEL
metaMS-2.1.3.dist-info/entry_points.txt
metaMS-2.1.3.dist-info/top_level.txt
metaMS-2.1.3.dist-info/RECORD
