Metadata-Version: 2.1
Name: metaMS
Version: 2.1.3
Summary: Data processing, and annotation for metabolomics analysis by low-resolution GC-MS
Home-page: https://github.com/EMSL-Computing/MetaMS
Author: Corilo, Yuri
Author-email: corilo@pnnl.gov
License: BSD
Platform: UNKNOWN
Classifier: License :: OSI Approved :: BSD License
Classifier: Programming Language :: Python :: 3.6
Classifier: Programming Language :: Python :: 3.7
Requires-Dist: Click
Requires-Dist: CoreMS
Requires-Dist: requests
